{
    "match_id": "4781443",
    "map_name": "de_inferno",
    "score_str": "13 - 7",
    "score_t": 13,
    "score_ct": 7,
    "lobby_url": "https://cybershoke.net/match/4781443",
    "player_stats": [
        {
            "Player": "Ta9ess",
            "SteamID": "",
            "TeamNum": 0,
            "Kills": 11,
            "Deaths": 18,
            "Assists": 1,
            "K/D": 0.61,
            "ADR": 0,
            "HS%": 18.2,
            "Score": 0,
            "Damage": 0,
            "UtilityDamage": 0,
            "Flashed": 0,
            "TeamFlashed": 0,
            "FlashAssists": 0,
            "TotalSpent": 0,
            "EntryKills": 0,
            "EntryDeaths": 0,
            "ClutchWins": 0,
            "BaiterRating": 0,
            "BombPlants": 0,
            "BombDefuses": 0,
            "Headshots": 2,
            "MultiKills": {},
            "WeaponKills": {}
        },
        {
            "Player": "Ex1T",
            "SteamID": "",
            "TeamNum": 0,
            "Kills": 18,
            "Deaths": 10,
            "Assists": 9,
            "K/D": 1.8,
            "ADR": 0,
            "HS%": 66.7,
            "Score": 0,
            "Damage": 0,
            "UtilityDamage": 0,
            "Flashed": 0,
            "TeamFlashed": 0,
            "FlashAssists": 0,
            "TotalSpent": 0,
            "EntryKills": 0,
            "EntryDeaths": 0,
            "ClutchWins": 0,
            "BaiterRating": 0,
            "BombPlants": 0,
            "BombDefuses": 0,
            "Headshots": 12,
            "MultiKills": {},
            "WeaponKills": {}
        },
        {
            "Player": "Tbastina",
            "SteamID": "",
            "TeamNum": 0,
            "Kills": 14,
            "Deaths": 17,
            "Assists": 8,
            "K/D": 0.82,
            "ADR": 0,
            "HS%": 71.4,
            "Score": 0,
            "Damage": 0,
            "UtilityDamage": 0,
            "Flashed": 0,
            "TeamFlashed": 0,
            "FlashAssists": 0,
            "TotalSpent": 0,
            "EntryKills": 0,
            "EntryDeaths": 0,
            "ClutchWins": 0,
            "BaiterRating": 0,
            "BombPlants": 0,
            "BombDefuses": 0,
            "Headshots": 10,
            "MultiKills": {},
            "WeaponKills": {}
        },
        {
            "Player": "zbat",
            "SteamID": "",
            "TeamNum": 0,
            "Kills": 12,
            "Deaths": 18,
            "Assists": 4,
            "K/D": 0.67,
            "ADR": 0,
            "HS%": 33.3,
            "Score": 0,
            "Damage": 0,
            "UtilityDamage": 0,
            "Flashed": 0,
            "TeamFlashed": 0,
            "FlashAssists": 0,
            "TotalSpent": 0,
            "EntryKills": 0,
            "EntryDeaths": 0,
            "ClutchWins": 0,
            "BaiterRating": 0,
            "BombPlants": 0,
            "BombDefuses": 0,
            "Headshots": 4,
            "MultiKills": {},
            "WeaponKills": {}
        },
        {
            "Player": "Skeez",
            "SteamID": "",
            "TeamNum": 0,
            "Kills": 24,
            "Deaths": 13,
            "Assists": 7,
            "K/D": 1.85,
            "ADR": 0,
            "HS%": 41.7,
            "Score": 0,
            "Damage": 0,
            "UtilityDamage": 0,
            "Flashed": 0,
            "TeamFlashed": 0,
            "FlashAssists": 0,
            "TotalSpent": 0,
            "EntryKills": 0,
            "EntryDeaths": 0,
            "ClutchWins": 0,
            "BaiterRating": 0,
            "BombPlants": 0,
            "BombDefuses": 0,
            "Headshots": 10,
            "MultiKills": {},
            "WeaponKills": {}
        },
        {
            "Player": "Kim",
            "SteamID": "",
            "TeamNum": 0,
            "Kills": 19,
            "Deaths": 13,
            "Assists": 9,
            "K/D": 1.46,
            "ADR": 0,
            "HS%": 47.4,
            "Score": 0,
            "Damage": 0,
            "UtilityDamage": 0,
            "Flashed": 0,
            "TeamFlashed": 0,
            "FlashAssists": 0,
            "TotalSpent": 0,
            "EntryKills": 0,
            "EntryDeaths": 0,
            "ClutchWins": 0,
            "BaiterRating": 0,
            "BombPlants": 0,
            "BombDefuses": 0,
            "Headshots": 9,
            "MultiKills": {},
            "WeaponKills": {}
        },
        {
            "Player": "ABU_GHALI",
            "SteamID": "",
            "TeamNum": 0,
            "Kills": 15,
            "Deaths": 15,
            "Assists": 4,
            "K/D": 1.0,
            "ADR": 0,
            "HS%": 26.7,
            "Score": 0,
            "Damage": 0,
            "UtilityDamage": 0,
            "Flashed": 0,
            "TeamFlashed": 0,
            "FlashAssists": 0,
            "TotalSpent": 0,
            "EntryKills": 0,
            "EntryDeaths": 0,
            "ClutchWins": 0,
            "BaiterRating": 0,
            "BombPlants": 0,
            "BombDefuses": 0,
            "Headshots": 4,
            "MultiKills": {},
            "WeaponKills": {}
        },
        {
            "Player": "magon",
            "SteamID": "",
            "TeamNum": 0,
            "Kills": 16,
            "Deaths": 17,
            "Assists": 5,
            "K/D": 0.94,
            "ADR": 0,
            "HS%": 50.0,
            "Score": 0,
            "Damage": 0,
            "UtilityDamage": 0,
            "Flashed": 0,
            "TeamFlashed": 0,
            "FlashAssists": 0,
            "TotalSpent": 0,
            "EntryKills": 0,
            "EntryDeaths": 0,
            "ClutchWins": 0,
            "BaiterRating": 0,
            "BombPlants": 0,
            "BombDefuses": 0,
            "Headshots": 8,
            "MultiKills": {},
            "WeaponKills": {}
        },
        {
            "Player": "skandim",
            "SteamID": "",
            "TeamNum": 0,
            "Kills": 4,
            "Deaths": 19,
            "Assists": 4,
            "K/D": 0.21,
            "ADR": 0,
            "HS%": 50.0,
            "Score": 0,
            "Damage": 0,
            "UtilityDamage": 0,
            "Flashed": 0,
            "TeamFlashed": 0,
            "FlashAssists": 0,
            "TotalSpent": 0,
            "EntryKills": 0,
            "EntryDeaths": 0,
            "ClutchWins": 0,
            "BaiterRating": 0,
            "BombPlants": 0,
            "BombDefuses": 0,
            "Headshots": 2,
            "MultiKills": {},
            "WeaponKills": {}
        },
        {
            "Player": "Gastafix",
            "SteamID": "",
            "TeamNum": 0,
            "Kills": 14,
            "Deaths": 9,
            "Assists": 2,
            "K/D": 1.56,
            "ADR": 0,
            "HS%": 42.9,
            "Score": 0,
            "Damage": 0,
            "UtilityDamage": 0,
            "Flashed": 0,
            "TeamFlashed": 0,
            "FlashAssists": 0,
            "TotalSpent": 0,
            "EntryKills": 0,
            "EntryDeaths": 0,
            "ClutchWins": 0,
            "BaiterRating": 0,
            "BombPlants": 0,
            "BombDefuses": 0,
            "Headshots": 6,
            "MultiKills": {},
            "WeaponKills": {}
        }
    ]
}